ur_remote/Dashboard.py
ur_remote/Primary.py
ur_remote/PrimaryEnum.py
ur_remote/URRobot.py
ur_remote/__init__.py
ur_remote-0.1.3.dist-info/METADATA
ur_remote-0.1.3.dist-info/WHEEL
ur_remote-0.1.3.dist-info/top_level.txt
ur_remote-0.1.3.dist-info/RECORD
